pytantan/_mask.py
pytantan/py.typed
pytantan/lib.pyx
pytantan/_version.py
pytantan/.gitignore
pytantan/_mask.pyi
pytantan/__init__.py
pytantan/lib.pyi
pytantan/CMakeLists.txt
pytantan/lib.cpython-312-x86_64-linux-gnu.so
pytantan/tests/test_doctest.py
pytantan/tests/test_repeat_finder.py
pytantan/tests/test_mask.py
pytantan/tests/test_alphabet.py
pytantan/tests/__init__.py
pytantan/platform/generic.cpython-312-x86_64-linux-gnu.so
pytantan/platform/avx2.cpython-312-x86_64-linux-gnu.so
pytantan/platform/sse4.cpython-312-x86_64-linux-gnu.so
pytantan/platform/pxd.in
pytantan/platform/.gitignore
pytantan/platform/__init__.pxd
pytantan/platform/pyx.in
pytantan/platform/__init__.py
pytantan/platform/CMakeLists.txt
pytantan/tantan/lc.pxd
pytantan/tantan/utils.pxd
pytantan/tantan/__init__.pxd
pytantan/tantan/alphabet.pxd
pytantan/tantan/version.hh
pytantan/tantan/options.pxd
pytantan/tantan/score_matrix.pxd
pytantan-0.1.3.dist-info/RECORD
pytantan-0.1.3.dist-info/METADATA
pytantan-0.1.3.dist-info/WHEEL
pytantan-0.1.3.dist-info/licenses/COPYING
