Metadata-Version: 2.1
Name: pytantan
Version: 0.1.3
Summary: Cython bindings and Python interface to Tantan, a fast method for identifying repeats in DNA and protein sequences.
Keywords: bioinformatics,sequence,repeats,masking
Author-Email: Martin Larralde <martin.larralde@embl.de>
License:                     GNU GENERAL PUBLIC LICENSE
Classifier: Development Status :: 4 - Beta
Classifier: Intended Audience :: Developers
Classifier: Intended Audience :: Science/Research
Classifier: License :: OSI Approved :: MIT License
Classifier: Operating System :: OS Independent
Classifier: Programming Language :: C
Classifier: Programming Language :: Cython
Classifier: Programming Language :: Python :: 3.7
Classifier: Programming Language :: Python :: 3.8
Classifier: Programming Language :: Python :: 3.9
Classifier: Programming Language :: Python :: 3.10
Classifier: Programming Language :: Python :: 3.11
Classifier: Programming Language :: Python :: 3.12
Classifier: Programming Language :: Python :: Implementation :: CPython
Classifier: Programming Language :: Python :: Implementation :: PyPy
Classifier: Topic :: Scientific/Engineering :: Bio-Informatics
Classifier: Topic :: Scientific/Engineering :: Medical Science Apps.
Classifier: Typing :: Typed
Project-URL: Documentation, https://pytantan.readthedocs.io/en/stable/
Project-URL: Bug tracker, https://github.com/althonos/pytantan/issues
Project-URL: Changelog, https://github.com/althonos/pytantan/blob/main/CHANGELOG.md
Project-URL: Coverage, https://codecov.io/gh/althonos/pytantan/
Project-URL: Builds, https://github.com/althonos/pytantan/actions
Project-URL: Pypi, https://pypi.org/project/pytantan
Requires-Python: >=3.7
Requires-Dist: archspec~=0.2; os_name != "nt"
Requires-Dist: scoring-matrices~=0.3.0
Requires-Dist: importlib-resources; python_version < "3.9" and extra == "test"
Provides-Extra: test
